aliyunsdkmts/__init__.py
aliyunsdkmts/endpoint.py
aliyunsdkmts/request/__init__.py
aliyunsdkmts/request/v20140618/ActivateMediaWorkflowRequest.py
aliyunsdkmts/request/v20140618/AddMediaRequest.py
aliyunsdkmts/request/v20140618/AddMediaTagRequest.py
aliyunsdkmts/request/v20140618/AddMediaWorkflowRequest.py
aliyunsdkmts/request/v20140618/AddPipelineRequest.py
aliyunsdkmts/request/v20140618/AddSmarttagTemplateRequest.py
aliyunsdkmts/request/v20140618/AddTemplateRequest.py
aliyunsdkmts/request/v20140618/AddWaterMarkTemplateRequest.py
aliyunsdkmts/request/v20140618/BindInputBucketRequest.py
aliyunsdkmts/request/v20140618/BindOutputBucketRequest.py
aliyunsdkmts/request/v20140618/CancelJobRequest.py
aliyunsdkmts/request/v20140618/CreateCustomEntityRequest.py
aliyunsdkmts/request/v20140618/CreateCustomGroupRequest.py
aliyunsdkmts/request/v20140618/CreateFpShotDBRequest.py
aliyunsdkmts/request/v20140618/DeactivateMediaWorkflowRequest.py
aliyunsdkmts/request/v20140618/DeleteCustomEntityRequest.py
aliyunsdkmts/request/v20140618/DeleteCustomGroupRequest.py
aliyunsdkmts/request/v20140618/DeleteCustomViewRequest.py
aliyunsdkmts/request/v20140618/DeleteMediaRequest.py
aliyunsdkmts/request/v20140618/DeleteMediaTagRequest.py
aliyunsdkmts/request/v20140618/DeleteMediaWorkflowRequest.py
aliyunsdkmts/request/v20140618/DeletePipelineRequest.py
aliyunsdkmts/request/v20140618/DeleteSmarttagTemplateRequest.py
aliyunsdkmts/request/v20140618/DeleteTemplateRequest.py
aliyunsdkmts/request/v20140618/DeleteWaterMarkTemplateRequest.py
aliyunsdkmts/request/v20140618/ImAuditRequest.py
aliyunsdkmts/request/v20140618/ImportFpShotJobRequest.py
aliyunsdkmts/request/v20140618/ListAllMediaBucketRequest.py
aliyunsdkmts/request/v20140618/ListCustomEntitiesRequest.py
aliyunsdkmts/request/v20140618/ListCustomGroupsRequest.py
aliyunsdkmts/request/v20140618/ListCustomPersonsRequest.py
aliyunsdkmts/request/v20140618/ListCustomViewsRequest.py
aliyunsdkmts/request/v20140618/ListFpShotDBRequest.py
aliyun_python_sdk_mts-3.3.45.dist-info/LICENSE
aliyun_python_sdk_mts-3.3.45.dist-info/METADATA
aliyun_python_sdk_mts-3.3.45.dist-info/WHEEL
aliyun_python_sdk_mts-3.3.45.dist-info/top_level.txt
aliyun_python_sdk_mts-3.3.45.dist-info/RECORD
